{
  "metadata": {
    "benchmark_type": "DECOMPOSITION",
    "solver": "BENDERS_HIERARCHICAL",
    "n_farms": 25,
    "run_number": 1,
    "timestamp": "2025-11-26T22:02:29.103865"
  },
  "result": {
    "status": "failed",
    "objective_value": 0.4298113893644994,
    "solve_time": 8.158566236495972,
    "solver_time": 8.158566236495972,
    "success": false,
    "sample_id": 0,
    "n_units": 25,
    "total_area": 99.99,
    "n_foods": 27,
    "n_variables": 1350,
    "n_constraints": 35,
    "solver": "gurobi",
    "solution_areas": {
      "Farm_1_Beef": 0.0001,
      "Farm_1_Chicken": 0.0001,
      "Farm_1_Egg": 0.0001,
      "Farm_1_Lamb": 0.0001,
      "Farm_1_Pork": 0.0001,
      "Farm_1_Apple": 0.0001,
      "Farm_1_Avocado": 0.0001,
      "Farm_1_Banana": 0.0001,
      "Farm_1_Durian": 0.0001,
      "Farm_1_Guava": 0.0001,
      "Farm_1_Mango": 0.0001,
      "Farm_1_Orange": 0.0001,
      "Farm_1_Papaya": 0.0001,
      "Farm_1_Watermelon": 0.0001,
      "Farm_1_Chickpeas": 0.0001,
      "Farm_1_Peanuts": 0.0001,
      "Farm_1_Tempeh": 0.0001,
      "Farm_1_Tofu": 0.0001,
      "Farm_1_Corn": 0.0001,
      "Farm_1_Potato": 0.0001,
      "Farm_1_Cabbage": 0.0001,
      "Farm_1_Cucumber": 0.0001,
      "Farm_1_Eggplant": 0.0001,
      "Farm_1_Long bean": 0.0001,
      "Farm_1_Pumpkin": 0.0001,
      "Farm_1_Spinach": 4.9774000000000065,
      "Farm_1_Tomatoes": 0.0001,
      "Farm_2_Beef": 0.0001,
      "Farm_2_Chicken": 0.0001,
      "Farm_2_Egg": 0.0001,
      "Farm_2_Lamb": 0.0001,
      "Farm_2_Pork": 0.0001,
      "Farm_2_Apple": 0.0001,
      "Farm_2_Avocado": 0.0001,
      "Farm_2_Banana": 0.0001,
      "Farm_2_Durian": 0.0001,
      "Farm_2_Guava": 0.0001,
      "Farm_2_Mango": 0.0001,
      "Farm_2_Orange": 0.0001,
      "Farm_2_Papaya": 0.0001,
      "Farm_2_Watermelon": 0.0001,
      "Farm_2_Chickpeas": 0.0001,
      "Farm_2_Peanuts": 0.0001,
      "Farm_2_Tempeh": 0.0001,
      "Farm_2_Tofu": 0.0001,
      "Farm_2_Corn": 0.0001,
      "Farm_2_Potato": 0.0001,
      "Farm_2_Cabbage": 0.0001,
      "Farm_2_Cucumber": 0.0001,
      "Farm_2_Eggplant": 0.0001,
      "Farm_2_Long bean": 0.0001,
      "Farm_2_Pumpkin": 0.0001,
      "Farm_2_Spinach": 3.6273999999999944,
      "Farm_2_Tomatoes": 0.0001,
      "Farm_3_Beef": 0.0001,
      "Farm_3_Chicken": 0.0001,
      "Farm_3_Egg": 0.0001,
      "Farm_3_Lamb": 0.0001,
      "Farm_3_Pork": 0.0001,
      "Farm_3_Apple": 0.0001,
      "Farm_3_Avocado": 0.0001,
      "Farm_3_Banana": 0.0001,
      "Farm_3_Durian": 0.0001,
      "Farm_3_Guava": 0.0001,
      "Farm_3_Mango": 0.0001,
      "Farm_3_Orange": 0.0001,
      "Farm_3_Papaya": 0.0001,
      "Farm_3_Watermelon": 0.0001,
      "Farm_3_Chickpeas": 0.0001,
      "Farm_3_Peanuts": 0.0001,
      "Farm_3_Tempeh": 0.0001,
      "Farm_3_Tofu": 0.0001,
      "Farm_3_Corn": 0.0001,
      "Farm_3_Potato": 0.0001,
      "Farm_3_Cabbage": 0.0001,
      "Farm_3_Cucumber": 0.0001,
      "Farm_3_Eggplant": 0.0001,
      "Farm_3_Long bean": 0.0001,
      "Farm_3_Pumpkin": 0.0001,
      "Farm_3_Spinach": 5.367400000000006,
      "Farm_3_Tomatoes": 0.0001,
      "Farm_4_Beef": 0.0001,
      "Farm_4_Chicken": 0.0001,
      "Farm_4_Egg": 0.0001,
      "Farm_4_Lamb": 0.0001,
      "Farm_4_Pork": 0.0001,
      "Farm_4_Apple": 0.0001,
      "Farm_4_Avocado": 0.0001,
      "Farm_4_Banana": 0.0001,
      "Farm_4_Durian": 0.0001,
      "Farm_4_Guava": 0.0001,
      "Farm_4_Mango": 0.0001,
      "Farm_4_Orange": 0.0001,
      "Farm_4_Papaya": 0.0001,
      "Farm_4_Watermelon": 0.0001,
      "Farm_4_Chickpeas": 0.0001,
      "Farm_4_Peanuts": 0.0001,
      "Farm_4_Tempeh": 0.0001,
      "Farm_4_Tofu": 0.0001,
      "Farm_4_Corn": 0.0001,
      "Farm_4_Potato": 0.0001,
      "Farm_4_Cabbage": 0.0001,
      "Farm_4_Cucumber": 0.0001,
      "Farm_4_Eggplant": 0.0001,
      "Farm_4_Long bean": 0.0001,
      "Farm_4_Pumpkin": 0.0001,
      "Farm_4_Spinach": 8.317400000000006,
      "Farm_4_Tomatoes": 0.0001,
      "Farm_5_Beef": 0.0001,
      "Farm_5_Chicken": 0.0001,
      "Farm_5_Egg": 0.0001,
      "Farm_5_Lamb": 0.0001,
      "Farm_5_Pork": 0.0001,
      "Farm_5_Apple": 0.0001,
      "Farm_5_Avocado": 0.0001,
      "Farm_5_Banana": 0.0001,
      "Farm_5_Durian": 0.0001,
      "Farm_5_Guava": 0.0001,
      "Farm_5_Mango": 0.0001,
      "Farm_5_Orange": 0.0001,
      "Farm_5_Papaya": 0.0001,
      "Farm_5_Watermelon": 0.0001,
      "Farm_5_Chickpeas": 0.0001,
      "Farm_5_Peanuts": 0.0001,
      "Farm_5_Tempeh": 0.0001,
      "Farm_5_Tofu": 0.0001,
      "Farm_5_Corn": 0.0001,
      "Farm_5_Potato": 0.0001,
      "Farm_5_Cabbage": 0.0001,
      "Farm_5_Cucumber": 0.0001,
      "Farm_5_Eggplant": 0.0001,
      "Farm_5_Long bean": 0.0001,
      "Farm_5_Pumpkin": 0.0001,
      "Farm_5_Spinach": 3.4573999999999945,
      "Farm_5_Tomatoes": 0.0001,
      "Farm_6_Beef": 0.0001,
      "Farm_6_Chicken": 0.0001,
      "Farm_6_Egg": 0.0001,
      "Farm_6_Lamb": 0.0001,
      "Farm_6_Pork": 0.0001,
      "Farm_6_Apple": 0.0001,
      "Farm_6_Avocado": 0.0001,
      "Farm_6_Banana": 0.0001,
      "Farm_6_Durian": 0.0001,
      "Farm_6_Guava": 0.0001,
      "Farm_6_Mango": 0.0001,
      "Farm_6_Orange": 0.0001,
      "Farm_6_Papaya": 0.0001,
      "Farm_6_Watermelon": 0.0001,
      "Farm_6_Chickpeas": 0.0001,
      "Farm_6_Peanuts": 0.0001,
      "Farm_6_Tempeh": 0.0001,
      "Farm_6_Tofu": 0.0001,
      "Farm_6_Corn": 0.0001,
      "Farm_6_Potato": 0.0001,
      "Farm_6_Cabbage": 0.0001,
      "Farm_6_Cucumber": 0.0001,
      "Farm_6_Eggplant": 0.0001,
      "Farm_6_Long bean": 0.0001,
      "Farm_6_Pumpkin": 0.0001,
      "Farm_6_Spinach": 3.4573999999999945,
      "Farm_6_Tomatoes": 0.0001,
      "Farm_7_Beef": 0.0001,
      "Farm_7_Chicken": 0.0001,
      "Farm_7_Egg": 0.0001,
      "Farm_7_Lamb": 0.0001,
      "Farm_7_Pork": 0.0001,
      "Farm_7_Apple": 0.0001,
      "Farm_7_Avocado": 0.0001,
      "Farm_7_Banana": 0.0001,
      "Farm_7_Durian": 0.0001,
      "Farm_7_Guava": 0.0001,
      "Farm_7_Mango": 0.0001,
      "Farm_7_Orange": 0.0001,
      "Farm_7_Papaya": 0.0001,
      "Farm_7_Watermelon": 0.0001,
      "Farm_7_Chickpeas": 0.0001,
      "Farm_7_Peanuts": 0.0001,
      "Farm_7_Tempeh": 0.0001,
      "Farm_7_Tofu": 0.0001,
      "Farm_7_Corn": 0.0001,
      "Farm_7_Potato": 0.0001,
      "Farm_7_Cabbage": 0.0001,
      "Farm_7_Cucumber": 0.0001,
      "Farm_7_Eggplant": 0.0001,
      "Farm_7_Long bean": 0.0001,
      "Farm_7_Pumpkin": 0.0001,
      "Farm_7_Spinach": 8.557400000000007,
      "Farm_7_Tomatoes": 0.0001,
      "Farm_8_Beef": 0.0001,
      "Farm_8_Chicken": 0.0001,
      "Farm_8_Egg": 0.0001,
      "Farm_8_Lamb": 0.0001,
      "Farm_8_Pork": 0.0001,
      "Farm_8_Apple": 0.0001,
      "Farm_8_Avocado": 0.0001,
      "Farm_8_Banana": 0.0001,
      "Farm_8_Durian": 0.0001,
      "Farm_8_Guava": 0.0001,
      "Farm_8_Mango": 0.0001,
      "Farm_8_Orange": 0.0001,
      "Farm_8_Papaya": 0.0001,
      "Farm_8_Watermelon": 0.0001,
      "Farm_8_Chickpeas": 0.0001,
      "Farm_8_Peanuts": 0.0001,
      "Farm_8_Tempeh": 0.0001,
      "Farm_8_Tofu": 0.0001,
      "Farm_8_Corn": 0.0001,
      "Farm_8_Potato": 0.0001,
      "Farm_8_Cabbage": 0.0001,
      "Farm_8_Cucumber": 0.0001,
      "Farm_8_Eggplant": 0.0001,
      "Farm_8_Long bean": 0.0001,
      "Farm_8_Pumpkin": 0.0001,
      "Farm_8_Spinach": 5.697400000000006,
      "Farm_8_Tomatoes": 0.0001,
      "Farm_9_Beef": 0.0001,
      "Farm_9_Chicken": 0.0001,
      "Farm_9_Egg": 0.0001,
      "Farm_9_Lamb": 0.0001,
      "Farm_9_Pork": 0.0001,
      "Farm_9_Apple": 0.0001,
      "Farm_9_Avocado": 0.0001,
      "Farm_9_Banana": 0.0001,
      "Farm_9_Durian": 0.0001,
      "Farm_9_Guava": 0.0001,
      "Farm_9_Mango": 0.0001,
      "Farm_9_Orange": 0.0001,
      "Farm_9_Papaya": 0.0001,
      "Farm_9_Watermelon": 0.0001,
      "Farm_9_Chickpeas": 0.0001,
      "Farm_9_Peanuts": 0.0001,
      "Farm_9_Tempeh": 0.0001,
      "Farm_9_Tofu": 0.0001,
      "Farm_9_Corn": 0.0001,
      "Farm_9_Potato": 0.0001,
      "Farm_9_Cabbage": 0.0001,
      "Farm_9_Cucumber": 0.0001,
      "Farm_9_Eggplant": 0.0001,
      "Farm_9_Long bean": 0.0001,
      "Farm_9_Pumpkin": 0.0001,
      "Farm_9_Spinach": 3.0673999999999944,
      "Farm_9_Tomatoes": 0.0001,
      "Farm_10_Beef": 0.0001,
      "Farm_10_Chicken": 0.0001,
      "Farm_10_Egg": 0.0001,
      "Farm_10_Lamb": 0.0001,
      "Farm_10_Pork": 0.0001,
      "Farm_10_Apple": 0.0001,
      "Farm_10_Avocado": 0.0001,
      "Farm_10_Banana": 0.0001,
      "Farm_10_Durian": 0.0001,
      "Farm_10_Guava": 0.0001,
      "Farm_10_Mango": 0.0001,
      "Farm_10_Orange": 0.0001,
      "Farm_10_Papaya": 0.0001,
      "Farm_10_Watermelon": 0.0001,
      "Farm_10_Chickpeas": 0.0001,
      "Farm_10_Peanuts": 0.0001,
      "Farm_10_Tempeh": 0.0001,
      "Farm_10_Tofu": 0.0001,
      "Farm_10_Corn": 0.0001,
      "Farm_10_Potato": 0.0001,
      "Farm_10_Cabbage": 0.0001,
      "Farm_10_Cucumber": 0.0001,
      "Farm_10_Eggplant": 0.0001,
      "Farm_10_Long bean": 0.0001,
      "Farm_10_Pumpkin": 0.0001,
      "Farm_10_Spinach": 5.097400000000006,
      "Farm_10_Tomatoes": 0.0001,
      "Farm_11_Beef": 0.0001,
      "Farm_11_Chicken": 0.0001,
      "Farm_11_Egg": 0.0001,
      "Farm_11_Lamb": 0.0001,
      "Farm_11_Pork": 0.0001,
      "Farm_11_Apple": 0.0001,
      "Farm_11_Avocado": 0.0001,
      "Farm_11_Banana": 0.0001,
      "Farm_11_Durian": 0.0001,
      "Farm_11_Guava": 0.0001,
      "Farm_11_Mango": 0.0001,
      "Farm_11_Orange": 0.0001,
      "Farm_11_Papaya": 0.0001,
      "Farm_11_Watermelon": 0.0001,
      "Farm_11_Chickpeas": 0.0001,
      "Farm_11_Peanuts": 0.0001,
      "Farm_11_Tempeh": 0.0001,
      "Farm_11_Tofu": 0.0001,
      "Farm_11_Corn": 0.0001,
      "Farm_11_Potato": 0.0001,
      "Farm_11_Cabbage": 0.0001,
      "Farm_11_Cucumber": 0.0001,
      "Farm_11_Eggplant": 0.0001,
      "Farm_11_Long bean": 0.0001,
      "Farm_11_Pumpkin": 0.0001,
      "Farm_11_Spinach": 3.0773999999999946,
      "Farm_11_Tomatoes": 0.0001,
      "Farm_12_Beef": 0.0001,
      "Farm_12_Chicken": 0.0001,
      "Farm_12_Egg": 0.0001,
      "Farm_12_Lamb": 0.0001,
      "Farm_12_Pork": 0.0001,
      "Farm_12_Apple": 0.0001,
      "Farm_12_Avocado": 0.0001,
      "Farm_12_Banana": 0.0001,
      "Farm_12_Durian": 0.0001,
      "Farm_12_Guava": 0.0001,
      "Farm_12_Mango": 0.0001,
      "Farm_12_Orange": 0.0001,
      "Farm_12_Papaya": 0.0001,
      "Farm_12_Watermelon": 0.0001,
      "Farm_12_Chickpeas": 0.0001,
      "Farm_12_Peanuts": 0.0001,
      "Farm_12_Tempeh": 0.0001,
      "Farm_12_Tofu": 0.0001,
      "Farm_12_Corn": 0.0001,
      "Farm_12_Potato": 0.0001,
      "Farm_12_Cabbage": 0.0001,
      "Farm_12_Cucumber": 0.0001,
      "Farm_12_Eggplant": 0.0001,
      "Farm_12_Long bean": 0.0001,
      "Farm_12_Pumpkin": 0.0001,
      "Farm_12_Spinach": 3.0773999999999946,
      "Farm_12_Tomatoes": 0.0001,
      "Farm_13_Beef": 0.0,
      "Farm_13_Chicken": 0.0001,
      "Farm_13_Egg": 0.0001,
      "Farm_13_Lamb": 0.0001,
      "Farm_13_Pork": 0.0001,
      "Farm_13_Apple": 0.0001,
      "Farm_13_Avocado": 0.0001,
      "Farm_13_Banana": 0.0001,
      "Farm_13_Durian": 0.0001,
      "Farm_13_Guava": 0.0001,
      "Farm_13_Mango": 0.0001,
      "Farm_13_Orange": 0.0001,
      "Farm_13_Papaya": 0.0001,
      "Farm_13_Watermelon": 0.0001,
      "Farm_13_Chickpeas": 0.0001,
      "Farm_13_Peanuts": 0.0001,
      "Farm_13_Tempeh": 0.0001,
      "Farm_13_Tofu": 0.0001,
      "Farm_13_Corn": 0.0001,
      "Farm_13_Potato": 0.0001,
      "Farm_13_Cabbage": 0.0001,
      "Farm_13_Cucumber": 0.0001,
      "Farm_13_Eggplant": 0.0001,
      "Farm_13_Long bean": 0.0001,
      "Farm_13_Pumpkin": 0.0001,
      "Farm_13_Spinach": 4.3875000000000055,
      "Farm_13_Tomatoes": 0.0001,
      "Farm_14_Beef": 0.0001,
      "Farm_14_Chicken": 0.0001,
      "Farm_14_Egg": 0.0001,
      "Farm_14_Lamb": 0.0001,
      "Farm_14_Pork": 0.0001,
      "Farm_14_Apple": 0.0001,
      "Farm_14_Avocado": 0.0001,
      "Farm_14_Banana": 0.0001,
      "Farm_14_Durian": 0.0001,
      "Farm_14_Guava": 0.0001,
      "Farm_14_Mango": 0.0001,
      "Farm_14_Orange": 0.0001,
      "Farm_14_Papaya": 0.0001,
      "Farm_14_Watermelon": 0.0001,
      "Farm_14_Chickpeas": 0.0001,
      "Farm_14_Peanuts": 0.0001,
      "Farm_14_Tempeh": 0.0001,
      "Farm_14_Tofu": 0.0001,
      "Farm_14_Corn": 0.0001,
      "Farm_14_Potato": 0.0001,
      "Farm_14_Cabbage": 0.0001,
      "Farm_14_Cucumber": 0.0001,
      "Farm_14_Eggplant": 0.0001,
      "Farm_14_Long bean": 0.0001,
      "Farm_14_Pumpkin": 0.0001,
      "Farm_14_Spinach": 1.4874000000000003,
      "Farm_14_Tomatoes": 0.0001,
      "Farm_15_Beef": 0.0001,
      "Farm_15_Chicken": 0.0001,
      "Farm_15_Egg": 0.0001,
      "Farm_15_Lamb": 0.0001,
      "Farm_15_Pork": 0.0001,
      "Farm_15_Apple": 0.0001,
      "Farm_15_Avocado": 0.0001,
      "Farm_15_Banana": 0.0001,
      "Farm_15_Durian": 0.0001,
      "Farm_15_Guava": 0.0001,
      "Farm_15_Mango": 0.0001,
      "Farm_15_Orange": 0.0001,
      "Farm_15_Papaya": 0.0001,
      "Farm_15_Watermelon": 0.0001,
      "Farm_15_Chickpeas": 0.0001,
      "Farm_15_Peanuts": 0.0001,
      "Farm_15_Tempeh": 0.0001,
      "Farm_15_Tofu": 0.0001,
      "Farm_15_Corn": 0.0001,
      "Farm_15_Potato": 0.0001,
      "Farm_15_Cabbage": 0.0001,
      "Farm_15_Cucumber": 0.0001,
      "Farm_15_Eggplant": 0.0001,
      "Farm_15_Long bean": 0.0001,
      "Farm_15_Pumpkin": 0.0001,
      "Farm_15_Spinach": 1.6374000000000002,
      "Farm_15_Tomatoes": 0.0001,
      "Farm_16_Beef": 0.0001,
      "Farm_16_Chicken": 0.0001,
      "Farm_16_Egg": 0.0001,
      "Farm_16_Lamb": 0.0001,
      "Farm_16_Pork": 0.0001,
      "Farm_16_Apple": 0.0001,
      "Farm_16_Avocado": 0.0001,
      "Farm_16_Banana": 0.0001,
      "Farm_16_Durian": 0.0001,
      "Farm_16_Guava": 0.0001,
      "Farm_16_Mango": 0.0001,
      "Farm_16_Orange": 0.0001,
      "Farm_16_Papaya": 0.0001,
      "Farm_16_Watermelon": 0.0001,
      "Farm_16_Chickpeas": 0.0001,
      "Farm_16_Peanuts": 0.0001,
      "Farm_16_Tempeh": 0.0001,
      "Farm_16_Tofu": 0.0001,
      "Farm_16_Corn": 0.0001,
      "Farm_16_Potato": 0.0001,
      "Farm_16_Cabbage": 0.0001,
      "Farm_16_Cucumber": 0.0001,
      "Farm_16_Eggplant": 0.0001,
      "Farm_16_Long bean": 0.0001,
      "Farm_16_Pumpkin": 0.0001,
      "Farm_16_Spinach": 2.9273999999999947,
      "Farm_16_Tomatoes": 0.0001,
      "Farm_17_Beef": 0.0001,
      "Farm_17_Chicken": 0.0001,
      "Farm_17_Egg": 0.0001,
      "Farm_17_Lamb": 0.0001,
      "Farm_17_Pork": 0.0001,
      "Farm_17_Apple": 0.0001,
      "Farm_17_Avocado": 0.0001,
      "Farm_17_Banana": 0.0001,
      "Farm_17_Durian": 0.0001,
      "Farm_17_Guava": 0.0001,
      "Farm_17_Mango": 0.0001,
      "Farm_17_Orange": 0.0001,
      "Farm_17_Papaya": 0.0001,
      "Farm_17_Watermelon": 0.0001,
      "Farm_17_Chickpeas": 0.0001,
      "Farm_17_Peanuts": 0.0001,
      "Farm_17_Tempeh": 0.0001,
      "Farm_17_Tofu": 0.0001,
      "Farm_17_Corn": 0.0001,
      "Farm_17_Potato": 0.0001,
      "Farm_17_Cabbage": 0.0001,
      "Farm_17_Cucumber": 0.0001,
      "Farm_17_Eggplant": 0.0001,
      "Farm_17_Long bean": 0.0001,
      "Farm_17_Pumpkin": 0.0001,
      "Farm_17_Spinach": 2.3373999999999944,
      "Farm_17_Tomatoes": 0.0001,
      "Farm_18_Beef": 0.0001,
      "Farm_18_Chicken": 0.0001,
      "Farm_18_Egg": 0.0001,
      "Farm_18_Lamb": 0.0001,
      "Farm_18_Pork": 0.0001,
      "Farm_18_Apple": 0.0001,
      "Farm_18_Avocado": 0.0001,
      "Farm_18_Banana": 0.0001,
      "Farm_18_Durian": 0.0001,
      "Farm_18_Guava": 0.0001,
      "Farm_18_Mango": 0.0001,
      "Farm_18_Orange": 0.0001,
      "Farm_18_Papaya": 0.0001,
      "Farm_18_Watermelon": 0.0001,
      "Farm_18_Chickpeas": 0.0001,
      "Farm_18_Peanuts": 0.0001,
      "Farm_18_Tempeh": 0.0001,
      "Farm_18_Tofu": 0.0001,
      "Farm_18_Corn": 0.0001,
      "Farm_18_Potato": 0.0001,
      "Farm_18_Cabbage": 0.0001,
      "Farm_18_Cucumber": 0.0001,
      "Farm_18_Eggplant": 0.0001,
      "Farm_18_Long bean": 0.0001,
      "Farm_18_Pumpkin": 0.0001,
      "Farm_18_Spinach": 4.547400000000006,
      "Farm_18_Tomatoes": 0.0001,
      "Farm_19_Beef": 0.0001,
      "Farm_19_Chicken": 0.0001,
      "Farm_19_Egg": 0.0001,
      "Farm_19_Lamb": 0.0001,
      "Farm_19_Pork": 0.0001,
      "Farm_19_Apple": 0.0001,
      "Farm_19_Avocado": 0.0001,
      "Farm_19_Banana": 0.0001,
      "Farm_19_Durian": 0.0001,
      "Farm_19_Guava": 0.0001,
      "Farm_19_Mango": 0.0001,
      "Farm_19_Orange": 0.0001,
      "Farm_19_Papaya": 0.0001,
      "Farm_19_Watermelon": 0.0001,
      "Farm_19_Chickpeas": 0.0001,
      "Farm_19_Peanuts": 0.0001,
      "Farm_19_Tempeh": 0.0001,
      "Farm_19_Tofu": 0.0001,
      "Farm_19_Corn": 0.0001,
      "Farm_19_Potato": 0.0001,
      "Farm_19_Cabbage": 0.0001,
      "Farm_19_Cucumber": 0.0001,
      "Farm_19_Eggplant": 0.0001,
      "Farm_19_Long bean": 0.0001,
      "Farm_19_Pumpkin": 0.0001,
      "Farm_19_Spinach": 2.4673999999999947,
      "Farm_19_Tomatoes": 0.0001,
      "Farm_20_Beef": 0.0001,
      "Farm_20_Chicken": 0.0001,
      "Farm_20_Egg": 0.0001,
      "Farm_20_Lamb": 0.0001,
      "Farm_20_Pork": 0.0001,
      "Farm_20_Apple": 0.0001,
      "Farm_20_Avocado": 0.0001,
      "Farm_20_Banana": 0.0001,
      "Farm_20_Durian": 0.0001,
      "Farm_20_Guava": 0.0001,
      "Farm_20_Mango": 0.0001,
      "Farm_20_Orange": 0.0001,
      "Farm_20_Papaya": 0.0001,
      "Farm_20_Watermelon": 0.0001,
      "Farm_20_Chickpeas": 0.0001,
      "Farm_20_Peanuts": 0.0001,
      "Farm_20_Tempeh": 0.0001,
      "Farm_20_Tofu": 0.0001,
      "Farm_20_Corn": 0.0001,
      "Farm_20_Potato": 0.0001,
      "Farm_20_Cabbage": 0.0001,
      "Farm_20_Cucumber": 0.0001,
      "Farm_20_Eggplant": 0.0001,
      "Farm_20_Long bean": 0.0001,
      "Farm_20_Pumpkin": 0.0001,
      "Farm_20_Spinach": 1.9174000000000002,
      "Farm_20_Tomatoes": 0.0001,
      "Farm_21_Beef": 0.0001,
      "Farm_21_Chicken": 0.0001,
      "Farm_21_Egg": 0.0001,
      "Farm_21_Lamb": 0.0001,
      "Farm_21_Pork": 0.0001,
      "Farm_21_Apple": 0.0001,
      "Farm_21_Avocado": 0.0001,
      "Farm_21_Banana": 0.0001,
      "Farm_21_Durian": 0.0001,
      "Farm_21_Guava": 0.0001,
      "Farm_21_Mango": 0.0001,
      "Farm_21_Orange": 0.0001,
      "Farm_21_Papaya": 0.0001,
      "Farm_21_Watermelon": 0.0001,
      "Farm_21_Chickpeas": 0.0001,
      "Farm_21_Peanuts": 0.0001,
      "Farm_21_Tempeh": 0.0001,
      "Farm_21_Tofu": 0.0001,
      "Farm_21_Corn": 0.0001,
      "Farm_21_Potato": 0.0001,
      "Farm_21_Cabbage": 0.0001,
      "Farm_21_Cucumber": 0.0001,
      "Farm_21_Eggplant": 0.0001,
      "Farm_21_Long bean": 0.0001,
      "Farm_21_Pumpkin": 0.0001,
      "Farm_21_Spinach": 8.087400000000006,
      "Farm_21_Tomatoes": 0.0001,
      "Farm_22_Beef": 0.0001,
      "Farm_22_Chicken": 0.0001,
      "Farm_22_Egg": 0.0001,
      "Farm_22_Lamb": 0.0001,
      "Farm_22_Pork": 0.0001,
      "Farm_22_Apple": 0.0001,
      "Farm_22_Avocado": 0.0001,
      "Farm_22_Banana": 0.0001,
      "Farm_22_Durian": 0.0001,
      "Farm_22_Guava": 0.0001,
      "Farm_22_Mango": 0.0001,
      "Farm_22_Orange": 0.0001,
      "Farm_22_Papaya": 0.0001,
      "Farm_22_Watermelon": 0.0001,
      "Farm_22_Chickpeas": 0.0001,
      "Farm_22_Peanuts": 0.0001,
      "Farm_22_Tempeh": 0.0001,
      "Farm_22_Tofu": 0.0001,
      "Farm_22_Corn": 0.0001,
      "Farm_22_Potato": 0.0001,
      "Farm_22_Cabbage": 0.0001,
      "Farm_22_Cucumber": 0.0001,
      "Farm_22_Eggplant": 0.0001,
      "Farm_22_Long bean": 0.0001,
      "Farm_22_Pumpkin": 0.0001,
      "Farm_22_Spinach": 3.4673999999999947,
      "Farm_22_Tomatoes": 0.0001,
      "Farm_23_Beef": 0.0,
      "Farm_23_Chicken": 0.0001,
      "Farm_23_Egg": 0.0001,
      "Farm_23_Lamb": 0.0001,
      "Farm_23_Pork": 0.0001,
      "Farm_23_Apple": 0.0001,
      "Farm_23_Avocado": 0.0001,
      "Farm_23_Banana": 0.0001,
      "Farm_23_Durian": 0.0001,
      "Farm_23_Guava": 0.0001,
      "Farm_23_Mango": 0.0001,
      "Farm_23_Orange": 0.0001,
      "Farm_23_Papaya": 0.0001,
      "Farm_23_Watermelon": 0.0001,
      "Farm_23_Chickpeas": 0.0001,
      "Farm_23_Peanuts": 0.0001,
      "Farm_23_Tempeh": 0.0001,
      "Farm_23_Tofu": 0.0001,
      "Farm_23_Corn": 0.0001,
      "Farm_23_Potato": 0.0001,
      "Farm_23_Cabbage": 0.0001,
      "Farm_23_Cucumber": 0.0001,
      "Farm_23_Eggplant": 0.0001,
      "Farm_23_Long bean": 0.0001,
      "Farm_23_Pumpkin": 0.0001,
      "Farm_23_Spinach": 4.017500000000005,
      "Farm_23_Tomatoes": 0.0001,
      "Farm_24_Beef": 0.0,
      "Farm_24_Chicken": 0.0001,
      "Farm_24_Egg": 0.0001,
      "Farm_24_Lamb": 0.0001,
      "Farm_24_Pork": 0.0001,
      "Farm_24_Apple": 0.0001,
      "Farm_24_Avocado": 0.0001,
      "Farm_24_Banana": 0.0001,
      "Farm_24_Durian": 0.0001,
      "Farm_24_Guava": 0.0001,
      "Farm_24_Mango": 0.0001,
      "Farm_24_Orange": 0.0001,
      "Farm_24_Papaya": 0.0001,
      "Farm_24_Watermelon": 0.0001,
      "Farm_24_Chickpeas": 0.0001,
      "Farm_24_Peanuts": 0.0001,
      "Farm_24_Tempeh": 0.0001,
      "Farm_24_Tofu": 0.0001,
      "Farm_24_Corn": 0.0001,
      "Farm_24_Potato": 0.0001,
      "Farm_24_Cabbage": 0.0001,
      "Farm_24_Cucumber": 0.0001,
      "Farm_24_Eggplant": 0.0001,
      "Farm_24_Long bean": 0.0001,
      "Farm_24_Pumpkin": 0.0001,
      "Farm_24_Spinach": 1.9075000000000002,
      "Farm_24_Tomatoes": 0.0001,
      "Farm_25_Beef": 0.0,
      "Farm_25_Chicken": 0.0001,
      "Farm_25_Egg": 0.0001,
      "Farm_25_Lamb": 0.0001,
      "Farm_25_Pork": 0.0001,
      "Farm_25_Apple": 0.0001,
      "Farm_25_Avocado": 0.0001,
      "Farm_25_Banana": 0.0001,
      "Farm_25_Durian": 0.0001,
      "Farm_25_Guava": 0.0001,
      "Farm_25_Mango": 0.0001,
      "Farm_25_Orange": 0.0001,
      "Farm_25_Papaya": 0.0001,
      "Farm_25_Watermelon": 0.0001,
      "Farm_25_Chickpeas": 0.0001,
      "Farm_25_Peanuts": 0.0001,
      "Farm_25_Tempeh": 0.0001,
      "Farm_25_Tofu": 0.0001,
      "Farm_25_Corn": 0.0001,
      "Farm_25_Potato": 0.0001,
      "Farm_25_Cabbage": 0.0001,
      "Farm_25_Cucumber": 0.0001,
      "Farm_25_Eggplant": 0.0001,
      "Farm_25_Long bean": 0.0001,
      "Farm_25_Pumpkin": 0.0001,
      "Farm_25_Spinach": 2.9574999999999947,
      "Farm_25_Tomatoes": 0.0001
    },
    "solution_selections": {
      "Farm_1_Beef": 1.0,
      "Farm_1_Chicken": 1.0,
      "Farm_1_Egg": 1.0,
      "Farm_1_Lamb": 1.0,
      "Farm_1_Pork": 1.0,
      "Farm_1_Apple": 1.0,
      "Farm_1_Avocado": 1.0,
      "Farm_1_Banana": 1.0,
      "Farm_1_Durian": 1.0,
      "Farm_1_Guava": 1.0,
      "Farm_1_Mango": 1.0,
      "Farm_1_Orange": 1.0,
      "Farm_1_Papaya": 1.0,
      "Farm_1_Watermelon": 1.0,
      "Farm_1_Chickpeas": 1.0,
      "Farm_1_Peanuts": 1.0,
      "Farm_1_Tempeh": 1.0,
      "Farm_1_Tofu": 1.0,
      "Farm_1_Corn": 1.0,
      "Farm_1_Potato": 1.0,
      "Farm_1_Cabbage": 1.0,
      "Farm_1_Cucumber": 1.0,
      "Farm_1_Eggplant": 1.0,
      "Farm_1_Long bean": 1.0,
      "Farm_1_Pumpkin": 1.0,
      "Farm_1_Spinach": 1.0,
      "Farm_1_Tomatoes": 1.0,
      "Farm_2_Beef": 1.0,
      "Farm_2_Chicken": 1.0,
      "Farm_2_Egg": 1.0,
      "Farm_2_Lamb": 1.0,
      "Farm_2_Pork": 1.0,
      "Farm_2_Apple": 1.0,
      "Farm_2_Avocado": 1.0,
      "Farm_2_Banana": 1.0,
      "Farm_2_Durian": 1.0,
      "Farm_2_Guava": 1.0,
      "Farm_2_Mango": 1.0,
      "Farm_2_Orange": 1.0,
      "Farm_2_Papaya": 1.0,
      "Farm_2_Watermelon": 1.0,
      "Farm_2_Chickpeas": 1.0,
      "Farm_2_Peanuts": 1.0,
      "Farm_2_Tempeh": 1.0,
      "Farm_2_Tofu": 1.0,
      "Farm_2_Corn": 1.0,
      "Farm_2_Potato": 1.0,
      "Farm_2_Cabbage": 1.0,
      "Farm_2_Cucumber": 1.0,
      "Farm_2_Eggplant": 1.0,
      "Farm_2_Long bean": 1.0,
      "Farm_2_Pumpkin": 1.0,
      "Farm_2_Spinach": 1.0,
      "Farm_2_Tomatoes": 1.0,
      "Farm_3_Beef": 1.0,
      "Farm_3_Chicken": 1.0,
      "Farm_3_Egg": 1.0,
      "Farm_3_Lamb": 1.0,
      "Farm_3_Pork": 1.0,
      "Farm_3_Apple": 1.0,
      "Farm_3_Avocado": 1.0,
      "Farm_3_Banana": 1.0,
      "Farm_3_Durian": 1.0,
      "Farm_3_Guava": 1.0,
      "Farm_3_Mango": 1.0,
      "Farm_3_Orange": 1.0,
      "Farm_3_Papaya": 1.0,
      "Farm_3_Watermelon": 1.0,
      "Farm_3_Chickpeas": 1.0,
      "Farm_3_Peanuts": 1.0,
      "Farm_3_Tempeh": 1.0,
      "Farm_3_Tofu": 1.0,
      "Farm_3_Corn": 1.0,
      "Farm_3_Potato": 1.0,
      "Farm_3_Cabbage": 1.0,
      "Farm_3_Cucumber": 1.0,
      "Farm_3_Eggplant": 1.0,
      "Farm_3_Long bean": 1.0,
      "Farm_3_Pumpkin": 1.0,
      "Farm_3_Spinach": 1.0,
      "Farm_3_Tomatoes": 1.0,
      "Farm_4_Beef": 1.0,
      "Farm_4_Chicken": 1.0,
      "Farm_4_Egg": 1.0,
      "Farm_4_Lamb": 1.0,
      "Farm_4_Pork": 1.0,
      "Farm_4_Apple": 1.0,
      "Farm_4_Avocado": 1.0,
      "Farm_4_Banana": 1.0,
      "Farm_4_Durian": 1.0,
      "Farm_4_Guava": 1.0,
      "Farm_4_Mango": 1.0,
      "Farm_4_Orange": 1.0,
      "Farm_4_Papaya": 1.0,
      "Farm_4_Watermelon": 1.0,
      "Farm_4_Chickpeas": 1.0,
      "Farm_4_Peanuts": 1.0,
      "Farm_4_Tempeh": 1.0,
      "Farm_4_Tofu": 1.0,
      "Farm_4_Corn": 1.0,
      "Farm_4_Potato": 1.0,
      "Farm_4_Cabbage": 1.0,
      "Farm_4_Cucumber": 1.0,
      "Farm_4_Eggplant": 1.0,
      "Farm_4_Long bean": 1.0,
      "Farm_4_Pumpkin": 1.0,
      "Farm_4_Spinach": 1.0,
      "Farm_4_Tomatoes": 1.0,
      "Farm_5_Beef": 1.0,
      "Farm_5_Chicken": 1.0,
      "Farm_5_Egg": 1.0,
      "Farm_5_Lamb": 1.0,
      "Farm_5_Pork": 1.0,
      "Farm_5_Apple": 1.0,
      "Farm_5_Avocado": 1.0,
      "Farm_5_Banana": 1.0,
      "Farm_5_Durian": 1.0,
      "Farm_5_Guava": 1.0,
      "Farm_5_Mango": 1.0,
      "Farm_5_Orange": 1.0,
      "Farm_5_Papaya": 1.0,
      "Farm_5_Watermelon": 1.0,
      "Farm_5_Chickpeas": 1.0,
      "Farm_5_Peanuts": 1.0,
      "Farm_5_Tempeh": 1.0,
      "Farm_5_Tofu": 1.0,
      "Farm_5_Corn": 1.0,
      "Farm_5_Potato": 1.0,
      "Farm_5_Cabbage": 1.0,
      "Farm_5_Cucumber": 1.0,
      "Farm_5_Eggplant": 1.0,
      "Farm_5_Long bean": 1.0,
      "Farm_5_Pumpkin": 1.0,
      "Farm_5_Spinach": 1.0,
      "Farm_5_Tomatoes": 1.0,
      "Farm_6_Beef": 1.0,
      "Farm_6_Chicken": 1.0,
      "Farm_6_Egg": 1.0,
      "Farm_6_Lamb": 1.0,
      "Farm_6_Pork": 1.0,
      "Farm_6_Apple": 1.0,
      "Farm_6_Avocado": 1.0,
      "Farm_6_Banana": 1.0,
      "Farm_6_Durian": 1.0,
      "Farm_6_Guava": 1.0,
      "Farm_6_Mango": 1.0,
      "Farm_6_Orange": 1.0,
      "Farm_6_Papaya": 1.0,
      "Farm_6_Watermelon": 1.0,
      "Farm_6_Chickpeas": 1.0,
      "Farm_6_Peanuts": 1.0,
      "Farm_6_Tempeh": 1.0,
      "Farm_6_Tofu": 1.0,
      "Farm_6_Corn": 1.0,
      "Farm_6_Potato": 1.0,
      "Farm_6_Cabbage": 1.0,
      "Farm_6_Cucumber": 1.0,
      "Farm_6_Eggplant": 1.0,
      "Farm_6_Long bean": 1.0,
      "Farm_6_Pumpkin": 1.0,
      "Farm_6_Spinach": 1.0,
      "Farm_6_Tomatoes": 1.0,
      "Farm_7_Beef": 1.0,
      "Farm_7_Chicken": 1.0,
      "Farm_7_Egg": 1.0,
      "Farm_7_Lamb": 1.0,
      "Farm_7_Pork": 1.0,
      "Farm_7_Apple": 1.0,
      "Farm_7_Avocado": 1.0,
      "Farm_7_Banana": 1.0,
      "Farm_7_Durian": 1.0,
      "Farm_7_Guava": 1.0,
      "Farm_7_Mango": 1.0,
      "Farm_7_Orange": 1.0,
      "Farm_7_Papaya": 1.0,
      "Farm_7_Watermelon": 1.0,
      "Farm_7_Chickpeas": 1.0,
      "Farm_7_Peanuts": 1.0,
      "Farm_7_Tempeh": 1.0,
      "Farm_7_Tofu": 1.0,
      "Farm_7_Corn": 1.0,
      "Farm_7_Potato": 1.0,
      "Farm_7_Cabbage": 1.0,
      "Farm_7_Cucumber": 1.0,
      "Farm_7_Eggplant": 1.0,
      "Farm_7_Long bean": 1.0,
      "Farm_7_Pumpkin": 1.0,
      "Farm_7_Spinach": 1.0,
      "Farm_7_Tomatoes": 1.0,
      "Farm_8_Beef": 1.0,
      "Farm_8_Chicken": 1.0,
      "Farm_8_Egg": 1.0,
      "Farm_8_Lamb": 1.0,
      "Farm_8_Pork": 1.0,
      "Farm_8_Apple": 1.0,
      "Farm_8_Avocado": 1.0,
      "Farm_8_Banana": 1.0,
      "Farm_8_Durian": 1.0,
      "Farm_8_Guava": 1.0,
      "Farm_8_Mango": 1.0,
      "Farm_8_Orange": 1.0,
      "Farm_8_Papaya": 1.0,
      "Farm_8_Watermelon": 1.0,
      "Farm_8_Chickpeas": 1.0,
      "Farm_8_Peanuts": 1.0,
      "Farm_8_Tempeh": 1.0,
      "Farm_8_Tofu": 1.0,
      "Farm_8_Corn": 1.0,
      "Farm_8_Potato": 1.0,
      "Farm_8_Cabbage": 1.0,
      "Farm_8_Cucumber": 1.0,
      "Farm_8_Eggplant": 1.0,
      "Farm_8_Long bean": 1.0,
      "Farm_8_Pumpkin": 1.0,
      "Farm_8_Spinach": 1.0,
      "Farm_8_Tomatoes": 1.0,
      "Farm_9_Beef": 1.0,
      "Farm_9_Chicken": 1.0,
      "Farm_9_Egg": 1.0,
      "Farm_9_Lamb": 1.0,
      "Farm_9_Pork": 1.0,
      "Farm_9_Apple": 1.0,
      "Farm_9_Avocado": 1.0,
      "Farm_9_Banana": 1.0,
      "Farm_9_Durian": 1.0,
      "Farm_9_Guava": 1.0,
      "Farm_9_Mango": 1.0,
      "Farm_9_Orange": 1.0,
      "Farm_9_Papaya": 1.0,
      "Farm_9_Watermelon": 1.0,
      "Farm_9_Chickpeas": 1.0,
      "Farm_9_Peanuts": 1.0,
      "Farm_9_Tempeh": 1.0,
      "Farm_9_Tofu": 1.0,
      "Farm_9_Corn": 1.0,
      "Farm_9_Potato": 1.0,
      "Farm_9_Cabbage": 1.0,
      "Farm_9_Cucumber": 1.0,
      "Farm_9_Eggplant": 1.0,
      "Farm_9_Long bean": 1.0,
      "Farm_9_Pumpkin": 1.0,
      "Farm_9_Spinach": 1.0,
      "Farm_9_Tomatoes": 1.0,
      "Farm_10_Beef": 1.0,
      "Farm_10_Chicken": 1.0,
      "Farm_10_Egg": 1.0,
      "Farm_10_Lamb": 1.0,
      "Farm_10_Pork": 1.0,
      "Farm_10_Apple": 1.0,
      "Farm_10_Avocado": 1.0,
      "Farm_10_Banana": 1.0,
      "Farm_10_Durian": 1.0,
      "Farm_10_Guava": 1.0,
      "Farm_10_Mango": 1.0,
      "Farm_10_Orange": 1.0,
      "Farm_10_Papaya": 1.0,
      "Farm_10_Watermelon": 1.0,
      "Farm_10_Chickpeas": 1.0,
      "Farm_10_Peanuts": 1.0,
      "Farm_10_Tempeh": 1.0,
      "Farm_10_Tofu": 1.0,
      "Farm_10_Corn": 1.0,
      "Farm_10_Potato": 1.0,
      "Farm_10_Cabbage": 1.0,
      "Farm_10_Cucumber": 1.0,
      "Farm_10_Eggplant": 1.0,
      "Farm_10_Long bean": 1.0,
      "Farm_10_Pumpkin": 1.0,
      "Farm_10_Spinach": 1.0,
      "Farm_10_Tomatoes": 1.0,
      "Farm_11_Beef": 1.0,
      "Farm_11_Chicken": 1.0,
      "Farm_11_Egg": 1.0,
      "Farm_11_Lamb": 1.0,
      "Farm_11_Pork": 1.0,
      "Farm_11_Apple": 1.0,
      "Farm_11_Avocado": 1.0,
      "Farm_11_Banana": 1.0,
      "Farm_11_Durian": 1.0,
      "Farm_11_Guava": 1.0,
      "Farm_11_Mango": 1.0,
      "Farm_11_Orange": 1.0,
      "Farm_11_Papaya": 1.0,
      "Farm_11_Watermelon": 1.0,
      "Farm_11_Chickpeas": 1.0,
      "Farm_11_Peanuts": 1.0,
      "Farm_11_Tempeh": 1.0,
      "Farm_11_Tofu": 1.0,
      "Farm_11_Corn": 1.0,
      "Farm_11_Potato": 1.0,
      "Farm_11_Cabbage": 1.0,
      "Farm_11_Cucumber": 1.0,
      "Farm_11_Eggplant": 1.0,
      "Farm_11_Long bean": 1.0,
      "Farm_11_Pumpkin": 1.0,
      "Farm_11_Spinach": 1.0,
      "Farm_11_Tomatoes": 1.0,
      "Farm_12_Beef": 1.0,
      "Farm_12_Chicken": 1.0,
      "Farm_12_Egg": 1.0,
      "Farm_12_Lamb": 1.0,
      "Farm_12_Pork": 1.0,
      "Farm_12_Apple": 1.0,
      "Farm_12_Avocado": 1.0,
      "Farm_12_Banana": 1.0,
      "Farm_12_Durian": 1.0,
      "Farm_12_Guava": 1.0,
      "Farm_12_Mango": 1.0,
      "Farm_12_Orange": 1.0,
      "Farm_12_Papaya": 1.0,
      "Farm_12_Watermelon": 1.0,
      "Farm_12_Chickpeas": 1.0,
      "Farm_12_Peanuts": 1.0,
      "Farm_12_Tempeh": 1.0,
      "Farm_12_Tofu": 1.0,
      "Farm_12_Corn": 1.0,
      "Farm_12_Potato": 1.0,
      "Farm_12_Cabbage": 1.0,
      "Farm_12_Cucumber": 1.0,
      "Farm_12_Eggplant": 1.0,
      "Farm_12_Long bean": 1.0,
      "Farm_12_Pumpkin": 1.0,
      "Farm_12_Spinach": 1.0,
      "Farm_12_Tomatoes": 1.0,
      "Farm_13_Beef": 0.0,
      "Farm_13_Chicken": 1.0,
      "Farm_13_Egg": 1.0,
      "Farm_13_Lamb": 1.0,
      "Farm_13_Pork": 1.0,
      "Farm_13_Apple": 1.0,
      "Farm_13_Avocado": 1.0,
      "Farm_13_Banana": 1.0,
      "Farm_13_Durian": 1.0,
      "Farm_13_Guava": 1.0,
      "Farm_13_Mango": 1.0,
      "Farm_13_Orange": 1.0,
      "Farm_13_Papaya": 1.0,
      "Farm_13_Watermelon": 1.0,
      "Farm_13_Chickpeas": 1.0,
      "Farm_13_Peanuts": 1.0,
      "Farm_13_Tempeh": 1.0,
      "Farm_13_Tofu": 1.0,
      "Farm_13_Corn": 1.0,
      "Farm_13_Potato": 1.0,
      "Farm_13_Cabbage": 1.0,
      "Farm_13_Cucumber": 1.0,
      "Farm_13_Eggplant": 1.0,
      "Farm_13_Long bean": 1.0,
      "Farm_13_Pumpkin": 1.0,
      "Farm_13_Spinach": 1.0,
      "Farm_13_Tomatoes": 1.0,
      "Farm_14_Beef": 1.0,
      "Farm_14_Chicken": 1.0,
      "Farm_14_Egg": 1.0,
      "Farm_14_Lamb": 1.0,
      "Farm_14_Pork": 1.0,
      "Farm_14_Apple": 1.0,
      "Farm_14_Avocado": 1.0,
      "Farm_14_Banana": 1.0,
      "Farm_14_Durian": 1.0,
      "Farm_14_Guava": 1.0,
      "Farm_14_Mango": 1.0,
      "Farm_14_Orange": 1.0,
      "Farm_14_Papaya": 1.0,
      "Farm_14_Watermelon": 1.0,
      "Farm_14_Chickpeas": 1.0,
      "Farm_14_Peanuts": 1.0,
      "Farm_14_Tempeh": 1.0,
      "Farm_14_Tofu": 1.0,
      "Farm_14_Corn": 1.0,
      "Farm_14_Potato": 1.0,
      "Farm_14_Cabbage": 1.0,
      "Farm_14_Cucumber": 1.0,
      "Farm_14_Eggplant": 1.0,
      "Farm_14_Long bean": 1.0,
      "Farm_14_Pumpkin": 1.0,
      "Farm_14_Spinach": 1.0,
      "Farm_14_Tomatoes": 1.0,
      "Farm_15_Beef": 1.0,
      "Farm_15_Chicken": 1.0,
      "Farm_15_Egg": 1.0,
      "Farm_15_Lamb": 1.0,
      "Farm_15_Pork": 1.0,
      "Farm_15_Apple": 1.0,
      "Farm_15_Avocado": 1.0,
      "Farm_15_Banana": 1.0,
      "Farm_15_Durian": 1.0,
      "Farm_15_Guava": 1.0,
      "Farm_15_Mango": 1.0,
      "Farm_15_Orange": 1.0,
      "Farm_15_Papaya": 1.0,
      "Farm_15_Watermelon": 1.0,
      "Farm_15_Chickpeas": 1.0,
      "Farm_15_Peanuts": 1.0,
      "Farm_15_Tempeh": 1.0,
      "Farm_15_Tofu": 1.0,
      "Farm_15_Corn": 1.0,
      "Farm_15_Potato": 1.0,
      "Farm_15_Cabbage": 1.0,
      "Farm_15_Cucumber": 1.0,
      "Farm_15_Eggplant": 1.0,
      "Farm_15_Long bean": 1.0,
      "Farm_15_Pumpkin": 1.0,
      "Farm_15_Spinach": 1.0,
      "Farm_15_Tomatoes": 1.0,
      "Farm_16_Beef": 1.0,
      "Farm_16_Chicken": 1.0,
      "Farm_16_Egg": 1.0,
      "Farm_16_Lamb": 1.0,
      "Farm_16_Pork": 1.0,
      "Farm_16_Apple": 1.0,
      "Farm_16_Avocado": 1.0,
      "Farm_16_Banana": 1.0,
      "Farm_16_Durian": 1.0,
      "Farm_16_Guava": 1.0,
      "Farm_16_Mango": 1.0,
      "Farm_16_Orange": 1.0,
      "Farm_16_Papaya": 1.0,
      "Farm_16_Watermelon": 1.0,
      "Farm_16_Chickpeas": 1.0,
      "Farm_16_Peanuts": 1.0,
      "Farm_16_Tempeh": 1.0,
      "Farm_16_Tofu": 1.0,
      "Farm_16_Corn": 1.0,
      "Farm_16_Potato": 1.0,
      "Farm_16_Cabbage": 1.0,
      "Farm_16_Cucumber": 1.0,
      "Farm_16_Eggplant": 1.0,
      "Farm_16_Long bean": 1.0,
      "Farm_16_Pumpkin": 1.0,
      "Farm_16_Spinach": 1.0,
      "Farm_16_Tomatoes": 1.0,
      "Farm_17_Beef": 1.0,
      "Farm_17_Chicken": 1.0,
      "Farm_17_Egg": 1.0,
      "Farm_17_Lamb": 1.0,
      "Farm_17_Pork": 1.0,
      "Farm_17_Apple": 1.0,
      "Farm_17_Avocado": 1.0,
      "Farm_17_Banana": 1.0,
      "Farm_17_Durian": 1.0,
      "Farm_17_Guava": 1.0,
      "Farm_17_Mango": 1.0,
      "Farm_17_Orange": 1.0,
      "Farm_17_Papaya": 1.0,
      "Farm_17_Watermelon": 1.0,
      "Farm_17_Chickpeas": 1.0,
      "Farm_17_Peanuts": 1.0,
      "Farm_17_Tempeh": 1.0,
      "Farm_17_Tofu": 1.0,
      "Farm_17_Corn": 1.0,
      "Farm_17_Potato": 1.0,
      "Farm_17_Cabbage": 1.0,
      "Farm_17_Cucumber": 1.0,
      "Farm_17_Eggplant": 1.0,
      "Farm_17_Long bean": 1.0,
      "Farm_17_Pumpkin": 1.0,
      "Farm_17_Spinach": 1.0,
      "Farm_17_Tomatoes": 1.0,
      "Farm_18_Beef": 1.0,
      "Farm_18_Chicken": 1.0,
      "Farm_18_Egg": 1.0,
      "Farm_18_Lamb": 1.0,
      "Farm_18_Pork": 1.0,
      "Farm_18_Apple": 1.0,
      "Farm_18_Avocado": 1.0,
      "Farm_18_Banana": 1.0,
      "Farm_18_Durian": 1.0,
      "Farm_18_Guava": 1.0,
      "Farm_18_Mango": 1.0,
      "Farm_18_Orange": 1.0,
      "Farm_18_Papaya": 1.0,
      "Farm_18_Watermelon": 1.0,
      "Farm_18_Chickpeas": 1.0,
      "Farm_18_Peanuts": 1.0,
      "Farm_18_Tempeh": 1.0,
      "Farm_18_Tofu": 1.0,
      "Farm_18_Corn": 1.0,
      "Farm_18_Potato": 1.0,
      "Farm_18_Cabbage": 1.0,
      "Farm_18_Cucumber": 1.0,
      "Farm_18_Eggplant": 1.0,
      "Farm_18_Long bean": 1.0,
      "Farm_18_Pumpkin": 1.0,
      "Farm_18_Spinach": 1.0,
      "Farm_18_Tomatoes": 1.0,
      "Farm_19_Beef": 1.0,
      "Farm_19_Chicken": 1.0,
      "Farm_19_Egg": 1.0,
      "Farm_19_Lamb": 1.0,
      "Farm_19_Pork": 1.0,
      "Farm_19_Apple": 1.0,
      "Farm_19_Avocado": 1.0,
      "Farm_19_Banana": 1.0,
      "Farm_19_Durian": 1.0,
      "Farm_19_Guava": 1.0,
      "Farm_19_Mango": 1.0,
      "Farm_19_Orange": 1.0,
      "Farm_19_Papaya": 1.0,
      "Farm_19_Watermelon": 1.0,
      "Farm_19_Chickpeas": 1.0,
      "Farm_19_Peanuts": 1.0,
      "Farm_19_Tempeh": 1.0,
      "Farm_19_Tofu": 1.0,
      "Farm_19_Corn": 1.0,
      "Farm_19_Potato": 1.0,
      "Farm_19_Cabbage": 1.0,
      "Farm_19_Cucumber": 1.0,
      "Farm_19_Eggplant": 1.0,
      "Farm_19_Long bean": 1.0,
      "Farm_19_Pumpkin": 1.0,
      "Farm_19_Spinach": 1.0,
      "Farm_19_Tomatoes": 1.0,
      "Farm_20_Beef": 1.0,
      "Farm_20_Chicken": 1.0,
      "Farm_20_Egg": 1.0,
      "Farm_20_Lamb": 1.0,
      "Farm_20_Pork": 1.0,
      "Farm_20_Apple": 1.0,
      "Farm_20_Avocado": 1.0,
      "Farm_20_Banana": 1.0,
      "Farm_20_Durian": 1.0,
      "Farm_20_Guava": 1.0,
      "Farm_20_Mango": 1.0,
      "Farm_20_Orange": 1.0,
      "Farm_20_Papaya": 1.0,
      "Farm_20_Watermelon": 1.0,
      "Farm_20_Chickpeas": 1.0,
      "Farm_20_Peanuts": 1.0,
      "Farm_20_Tempeh": 1.0,
      "Farm_20_Tofu": 1.0,
      "Farm_20_Corn": 1.0,
      "Farm_20_Potato": 1.0,
      "Farm_20_Cabbage": 1.0,
      "Farm_20_Cucumber": 1.0,
      "Farm_20_Eggplant": 1.0,
      "Farm_20_Long bean": 1.0,
      "Farm_20_Pumpkin": 1.0,
      "Farm_20_Spinach": 1.0,
      "Farm_20_Tomatoes": 1.0,
      "Farm_21_Beef": 1.0,
      "Farm_21_Chicken": 1.0,
      "Farm_21_Egg": 1.0,
      "Farm_21_Lamb": 1.0,
      "Farm_21_Pork": 1.0,
      "Farm_21_Apple": 1.0,
      "Farm_21_Avocado": 1.0,
      "Farm_21_Banana": 1.0,
      "Farm_21_Durian": 1.0,
      "Farm_21_Guava": 1.0,
      "Farm_21_Mango": 1.0,
      "Farm_21_Orange": 1.0,
      "Farm_21_Papaya": 1.0,
      "Farm_21_Watermelon": 1.0,
      "Farm_21_Chickpeas": 1.0,
      "Farm_21_Peanuts": 1.0,
      "Farm_21_Tempeh": 1.0,
      "Farm_21_Tofu": 1.0,
      "Farm_21_Corn": 1.0,
      "Farm_21_Potato": 1.0,
      "Farm_21_Cabbage": 1.0,
      "Farm_21_Cucumber": 1.0,
      "Farm_21_Eggplant": 1.0,
      "Farm_21_Long bean": 1.0,
      "Farm_21_Pumpkin": 1.0,
      "Farm_21_Spinach": 1.0,
      "Farm_21_Tomatoes": 1.0,
      "Farm_22_Beef": 1.0,
      "Farm_22_Chicken": 1.0,
      "Farm_22_Egg": 1.0,
      "Farm_22_Lamb": 1.0,
      "Farm_22_Pork": 1.0,
      "Farm_22_Apple": 1.0,
      "Farm_22_Avocado": 1.0,
      "Farm_22_Banana": 1.0,
      "Farm_22_Durian": 1.0,
      "Farm_22_Guava": 1.0,
      "Farm_22_Mango": 1.0,
      "Farm_22_Orange": 1.0,
      "Farm_22_Papaya": 1.0,
      "Farm_22_Watermelon": 1.0,
      "Farm_22_Chickpeas": 1.0,
      "Farm_22_Peanuts": 1.0,
      "Farm_22_Tempeh": 1.0,
      "Farm_22_Tofu": 1.0,
      "Farm_22_Corn": 1.0,
      "Farm_22_Potato": 1.0,
      "Farm_22_Cabbage": 1.0,
      "Farm_22_Cucumber": 1.0,
      "Farm_22_Eggplant": 1.0,
      "Farm_22_Long bean": 1.0,
      "Farm_22_Pumpkin": 1.0,
      "Farm_22_Spinach": 1.0,
      "Farm_22_Tomatoes": 1.0,
      "Farm_23_Beef": 0.0,
      "Farm_23_Chicken": 1.0,
      "Farm_23_Egg": 1.0,
      "Farm_23_Lamb": 1.0,
      "Farm_23_Pork": 1.0,
      "Farm_23_Apple": 1.0,
      "Farm_23_Avocado": 1.0,
      "Farm_23_Banana": 1.0,
      "Farm_23_Durian": 1.0,
      "Farm_23_Guava": 1.0,
      "Farm_23_Mango": 1.0,
      "Farm_23_Orange": 1.0,
      "Farm_23_Papaya": 1.0,
      "Farm_23_Watermelon": 1.0,
      "Farm_23_Chickpeas": 1.0,
      "Farm_23_Peanuts": 1.0,
      "Farm_23_Tempeh": 1.0,
      "Farm_23_Tofu": 1.0,
      "Farm_23_Corn": 1.0,
      "Farm_23_Potato": 1.0,
      "Farm_23_Cabbage": 1.0,
      "Farm_23_Cucumber": 1.0,
      "Farm_23_Eggplant": 1.0,
      "Farm_23_Long bean": 1.0,
      "Farm_23_Pumpkin": 1.0,
      "Farm_23_Spinach": 1.0,
      "Farm_23_Tomatoes": 1.0,
      "Farm_24_Beef": 0.0,
      "Farm_24_Chicken": 1.0,
      "Farm_24_Egg": 1.0,
      "Farm_24_Lamb": 1.0,
      "Farm_24_Pork": 1.0,
      "Farm_24_Apple": 1.0,
      "Farm_24_Avocado": 1.0,
      "Farm_24_Banana": 1.0,
      "Farm_24_Durian": 1.0,
      "Farm_24_Guava": 1.0,
      "Farm_24_Mango": 1.0,
      "Farm_24_Orange": 1.0,
      "Farm_24_Papaya": 1.0,
      "Farm_24_Watermelon": 1.0,
      "Farm_24_Chickpeas": 1.0,
      "Farm_24_Peanuts": 1.0,
      "Farm_24_Tempeh": 1.0,
      "Farm_24_Tofu": 1.0,
      "Farm_24_Corn": 1.0,
      "Farm_24_Potato": 1.0,
      "Farm_24_Cabbage": 1.0,
      "Farm_24_Cucumber": 1.0,
      "Farm_24_Eggplant": 1.0,
      "Farm_24_Long bean": 1.0,
      "Farm_24_Pumpkin": 1.0,
      "Farm_24_Spinach": 1.0,
      "Farm_24_Tomatoes": 1.0,
      "Farm_25_Beef": 0.0,
      "Farm_25_Chicken": 1.0,
      "Farm_25_Egg": 1.0,
      "Farm_25_Lamb": 1.0,
      "Farm_25_Pork": 1.0,
      "Farm_25_Apple": 1.0,
      "Farm_25_Avocado": 1.0,
      "Farm_25_Banana": 1.0,
      "Farm_25_Durian": 1.0,
      "Farm_25_Guava": 1.0,
      "Farm_25_Mango": 1.0,
      "Farm_25_Orange": 1.0,
      "Farm_25_Papaya": 1.0,
      "Farm_25_Watermelon": 1.0,
      "Farm_25_Chickpeas": 1.0,
      "Farm_25_Peanuts": 1.0,
      "Farm_25_Tempeh": 1.0,
      "Farm_25_Tofu": 1.0,
      "Farm_25_Corn": 1.0,
      "Farm_25_Potato": 1.0,
      "Farm_25_Cabbage": 1.0,
      "Farm_25_Cucumber": 1.0,
      "Farm_25_Eggplant": 1.0,
      "Farm_25_Long bean": 1.0,
      "Farm_25_Pumpkin": 1.0,
      "Farm_25_Spinach": 1.0,
      "Farm_25_Tomatoes": 1.0
    },
    "total_covered_area": 99.99,
    "solution_summary": {
      "total_allocated": 99.99,
      "total_available": 99.99,
      "idle_area": 0.0,
      "utilization": 1.0
    },
    "validation": {
      "is_feasible": false,
      "n_violations": 5,
      "violations": [
        {
          "constraint": "food_group_Animal-source foods",
          "type": "food_group_min_violation",
          "group": "Animal-source foods",
          "required_min": 2,
          "actual": 0,
          "deficit": 2
        },
        {
          "constraint": "food_group_Fruits",
          "type": "food_group_min_violation",
          "group": "Fruits",
          "required_min": 2,
          "actual": 0,
          "deficit": 2
        },
        {
          "constraint": "food_group_Pulses, nuts, and seeds",
          "type": "food_group_min_violation",
          "group": "Pulses, nuts, and seeds",
          "required_min": 2,
          "actual": 0,
          "deficit": 2
        },
        {
          "constraint": "food_group_Starchy staples",
          "type": "food_group_min_violation",
          "group": "Starchy staples",
          "required_min": 2,
          "actual": 0,
          "deficit": 2
        },
        {
          "constraint": "food_group_Vegetables",
          "type": "food_group_min_violation",
          "group": "Vegetables",
          "required_min": 2,
          "actual": 0,
          "deficit": 2
        }
      ],
      "constraint_checks": {
        "land_availability_Farm_1": {
          "type": "land_capacity",
          "limit": 4.98,
          "actual": 0.0,
          "satisfied": "True"
        },
        "land_availability_Farm_2": {
          "type": "land_capacity",
          "limit": 3.63,
          "actual": 0.0,
          "satisfied": "True"
        },
        "land_availability_Farm_3": {
          "type": "land_capacity",
          "limit": 5.37,
          "actual": 0.0,
          "satisfied": "True"
        },
        "land_availability_Farm_4": {
          "type": "land_capacity",
          "limit": 8.32,
          "actual": 0.0,
          "satisfied": "True"
        },
        "land_availability_Farm_5": {
          "type": "land_capacity",
          "limit": 3.46,
          "actual": 0.0,
          "satisfied": "True"
        },
        "land_availability_Farm_6": {
          "type": "land_capacity",
          "limit": 3.46,
          "actual": 0.0,
          "satisfied": "True"
        },
        "land_availability_Farm_7": {
          "type": "land_capacity",
          "limit": 8.56,
          "actual": 0.0,
          "satisfied": "True"
        },
        "land_availability_Farm_8": {
          "type": "land_capacity",
          "limit": 5.7,
          "actual": 0.0,
          "satisfied": "True"
        },
        "land_availability_Farm_9": {
          "type": "land_capacity",
          "limit": 3.07,
          "actual": 0.0,
          "satisfied": "True"
        },
        "land_availability_Farm_10": {
          "type": "land_capacity",
          "limit": 5.1,
          "actual": 0.0,
          "satisfied": "True"
        },
        "land_availability_Farm_11": {
          "type": "land_capacity",
          "limit": 3.08,
          "actual": 0.0,
          "satisfied": "True"
        },
        "land_availability_Farm_12": {
          "type": "land_capacity",
          "limit": 3.08,
          "actual": 0.0,
          "satisfied": "True"
        },
        "land_availability_Farm_13": {
          "type": "land_capacity",
          "limit": 4.39,
          "actual": 0.0,
          "satisfied": "True"
        },
        "land_availability_Farm_14": {
          "type": "land_capacity",
          "limit": 1.49,
          "actual": 0.0,
          "satisfied": "True"
        },
        "land_availability_Farm_15": {
          "type": "land_capacity",
          "limit": 1.64,
          "actual": 0.0,
          "satisfied": "True"
        },
        "land_availability_Farm_16": {
          "type": "land_capacity",
          "limit": 2.93,
          "actual": 0.0,
          "satisfied": "True"
        },
        "land_availability_Farm_17": {
          "type": "land_capacity",
          "limit": 2.34,
          "actual": 0.0,
          "satisfied": "True"
        },
        "land_availability_Farm_18": {
          "type": "land_capacity",
          "limit": 4.55,
          "actual": 0.0,
          "satisfied": "True"
        },
        "land_availability_Farm_19": {
          "type": "land_capacity",
          "limit": 2.47,
          "actual": 0.0,
          "satisfied": "True"
        },
        "land_availability_Farm_20": {
          "type": "land_capacity",
          "limit": 1.92,
          "actual": 0.0,
          "satisfied": "True"
        },
        "land_availability_Farm_21": {
          "type": "land_capacity",
          "limit": 8.09,
          "actual": 0.0,
          "satisfied": "True"
        },
        "land_availability_Farm_22": {
          "type": "land_capacity",
          "limit": 3.47,
          "actual": 0.0,
          "satisfied": "True"
        },
        "land_availability_Farm_23": {
          "type": "land_capacity",
          "limit": 4.02,
          "actual": 0.0,
          "satisfied": "True"
        },
        "land_availability_Farm_24": {
          "type": "land_capacity",
          "limit": 1.91,
          "actual": 0.0,
          "satisfied": "True"
        },
        "land_availability_Farm_25": {
          "type": "land_capacity",
          "limit": 2.96,
          "actual": 0.0,
          "satisfied": "True"
        },
        "food_group_Animal-source foods": {
          "type": "food_group_unique_count",
          "min": 2,
          "max": 15,
          "actual": 0,
          "satisfied": false
        },
        "food_group_Fruits": {
          "type": "food_group_unique_count",
          "min": 2,
          "max": 27,
          "actual": 0,
          "satisfied": false
        },
        "food_group_Pulses, nuts, and seeds": {
          "type": "food_group_unique_count",
          "min": 2,
          "max": 12,
          "actual": 0,
          "satisfied": false
        },
        "food_group_Starchy staples": {
          "type": "food_group_unique_count",
          "min": 2,
          "max": 6,
          "actual": 0,
          "satisfied": false
        },
        "food_group_Vegetables": {
          "type": "food_group_unique_count",
          "min": 2,
          "max": 21,
          "actual": 0,
          "satisfied": false
        }
      },
      "summary": "Infeasible: 5 violations found"
    },
    "error": null
  },
  "decomposition_specific": {
    "iterations_detail": [
      {
        "iteration": 1,
        "partition_size": 132,
        "energy": -302174.24553594657,
        "solve_time": 0.8619048595428467
      },
      {
        "iteration": 2,
        "partition_size": 150,
        "energy": -271140.8947072969,
        "solve_time": 1.093754529953003
      },
      {
        "iteration": 3,
        "partition_size": 150,
        "energy": -194756.11850680842,
        "solve_time": 0.8477656841278076
      },
      {
        "iteration": 4,
        "partition_size": 150,
        "energy": -273255.0951024727,
        "solve_time": 1.1952004432678223
      },
      {
        "iteration": 5,
        "partition_size": 150,
        "energy": -349227.94476457,
        "solve_time": 1.3022332191467285
      }
    ],
    "n_partitions": 5,
    "partition_sizes": [
      132,
      150,
      150,
      150,
      150
    ],
    "flip_decisions": {
      "0": 0,
      "1": 0,
      "2": 0,
      "3": 0,
      "4": 0
    },
    "partition_energies": [
      -302174.24553594657,
      -271140.8947072969,
      -194756.11850680842,
      -273255.0951024727,
      -349227.94476457
    ],
    "hierarchical": true,
    "qpu_time_total": 5.300858736038208,
    "used_qpu": false
  },
  "benchmark_info": {
    "n_farms": 25,
    "n_foods": 27,
    "total_land": 100.0,
    "max_embeddable_vars": 150,
    "use_qpu": false,
    "timestamp": "2025-11-26T22:02:29.104478"
  }
}